uopen.py
universal_open-0.1.0.dist-info/METADATA
universal_open-0.1.0.dist-info/WHEEL
universal_open-0.1.0.dist-info/entry_points.txt
universal_open-0.1.0.dist-info/RECORD
